setup.py
almost_p2p_chat/__init__.py
almost_p2p_chat/client.py
almost_p2p_chat/message.py
almost_p2p_chat/my_socket.py
almost_p2p_chat/server.py
almost_p2p_chat/user.py
almost_p2p_messenget.egg-info/PKG-INFO
almost_p2p_messenget.egg-info/SOURCES.txt
almost_p2p_messenget.egg-info/dependency_links.txt
almost_p2p_messenget.egg-info/top_level.txt